openml_pytorch/__init__.py
openml_pytorch/callbacks/__init__.py
openml_pytorch/callbacks/annealing.py
openml_pytorch/callbacks/callback.py
openml_pytorch/callbacks/device_callbacks.py
openml_pytorch/callbacks/helper.py
openml_pytorch/callbacks/recording.py
openml_pytorch/callbacks/tensorboard.py
openml_pytorch/callbacks/training_callbacks.py
openml_pytorch/config.py
openml_pytorch/custom_datasets/__init__.py
openml_pytorch/custom_datasets/generic_dataset.py
openml_pytorch/custom_datasets/image_dataset.py
openml_pytorch/custom_datasets/tabular_dataset.py
openml_pytorch/extension.py
openml_pytorch/layers/__init__.py
openml_pytorch/layers/functional.py
openml_pytorch/metrics.py
openml_pytorch/run_utils.py
openml_pytorch/trainer.py
openml_pytorch-0.1.7.dist-info/LICENSE.md
openml_pytorch-0.1.7.dist-info/METADATA
openml_pytorch-0.1.7.dist-info/WHEEL
openml_pytorch-0.1.7.dist-info/RECORD
