Metadata-Version: 2.3
Name: openml-pytorch
Version: 0.1.7
Summary: Pytorch extension for OpenML
Author: SubhadityaMukherjee
Author-email: msubhaditya@gmail.com
Requires-Python: >=3.11
Classifier: Programming Language :: Python :: 3
Classifier: Programming Language :: Python :: 3.11
Classifier: Programming Language :: Python :: 3.12
Classifier: Programming Language :: Python :: 3.13
Requires-Dist: liac-arff (>=2.4.0)
Requires-Dist: matplotlib (>3.10)
Requires-Dist: minio
Requires-Dist: netron (>=8.2.1)
Requires-Dist: numpy (>=1.6.2)
Requires-Dist: onnx (>=1.17.0)
Requires-Dist: openml (>=0.15.1)
Requires-Dist: packaging
Requires-Dist: pandas (>=1.0.0)
Requires-Dist: pyarrow
Requires-Dist: python-dateutil
Requires-Dist: requests
Requires-Dist: scikit-learn (>=0.18)
Requires-Dist: scipy (>=0.13.3)
Requires-Dist: tensorboard (>=2.18.0)
Requires-Dist: torch (>=2.2.0)
Requires-Dist: torchvision (>=0.20.0)
Requires-Dist: tqdm
Requires-Dist: tqdm (>=4.67.1)
Requires-Dist: xmltodict
